mensajes/__init__.py
mensajes/adios/__init__.py
mensajes/adios/despedidas.py
mensajes/hola/__init__.py
mensajes/hola/saludos.py
test/__init__.py
test/test_adios.py
test/test_hola.py
Mensajes_pgrillo-6.0.dist-info/LICENSE
Mensajes_pgrillo-6.0.dist-info/METADATA
Mensajes_pgrillo-6.0.dist-info/WHEEL
Mensajes_pgrillo-6.0.dist-info/top_level.txt
Mensajes_pgrillo-6.0.dist-info/RECORD
