Metadata-Version: 2.1
Name: Mensajes-pgrillo
Version: 6.0
Summary: Este es un paquete de ejemplo
Home-page: http://PGRi.info
Author: Pietro Grillo
Author-email: yo@gmail.com
Classifier: Environment :: Console
Classifier: Intended Audience :: Developers
Classifier: License :: OSI Approved :: MIT License
Classifier: Operating System :: OS Independent
Classifier: Programming Language :: Python
Classifier: Programming Language :: Python :: 3.9
Classifier: Topic :: Utilities
License-File: LICENSE
Requires-Dist: numpy (>=1.24.2)
